amic/__init__.py
amic/binder.py
amic/decorators.py
amic/errors.py
amic/generator.py
amic/grammar.lark
amic/locate.py
amic/modules.py
amic/py.typed
amic/resolver.py
amic/semantics.py
amic/ast/dumps.py
amic/ast/model.py
amic/cli/__init__.py
amic/cli/lexers.py
amic/cli/main.py
amic/codegen/__init__.py
amic/codegen/clients.py
amic/codegen/emit.py
amic/codegen/enums.py
amic/codegen/errors.py
amic/codegen/events.py
amic/codegen/gateway.py
amic/codegen/http_mapping.py
amic/codegen/imports.py
amic/codegen/models.py
amic/codegen/models_service.py
amic/codegen/servers.py
amic/codegen/utils.py
amic/codegen/wellknown.py
amic/compilation/compiled.py
amic/compilation/pipeline.py
amic/parsing/parser.py
amirpc/__init__.py
amirpc/app.py
amirpc/config.py
amirpc/errors.py
amirpc/healthcheck.py
amirpc/runtime.py
amirpc/types.py
amirpc/context/__init__.py
amirpc/context/runtime.py
amirpc/context/user.py
amirpc/gateway/__init__.py
amirpc/gateway/runtime.py
amirpc-1.4.0.dist-info/METADATA
amirpc-1.4.0.dist-info/WHEEL
amirpc-1.4.0.dist-info/entry_points.txt
amirpc-1.4.0.dist-info/RECORD
