Metadata-Version: 2.4
Name: amirpc
Version: 1.4.0
Summary: NATS-based RPC framework with code generation and OpenTelemetry tracing
License-Expression: MIT
Keywords: code-generation,microservices,nats,opentelemetry,rpc
Classifier: Development Status :: 5 - Production/Stable
Classifier: Intended Audience :: Developers
Classifier: License :: OSI Approved :: MIT License
Classifier: Programming Language :: Python :: 3.13
Classifier: Topic :: Software Development :: Code Generators
Classifier: Topic :: System :: Distributed Computing
Classifier: Typing :: Typed
Requires-Python: >=3.13
Requires-Dist: aiohttp>=3.12.15
Requires-Dist: dnspython>=2.8.0
Requires-Dist: fast-depends>=3.0.5
Requires-Dist: nats-py[nkeys]>=2.12.0
Requires-Dist: opentelemetry-api>=1.36.0
Requires-Dist: opentelemetry-sdk>=1.36.0
Requires-Dist: pydantic>=2.11.7
Provides-Extra: compiler
Requires-Dist: black>=24.8.0; extra == 'compiler'
Requires-Dist: lark>=1.2.2; extra == 'compiler'
Requires-Dist: rich>=14.1.0; extra == 'compiler'
Requires-Dist: typer>=0.16.0; extra == 'compiler'
Provides-Extra: gateway
Requires-Dist: fastapi>=0.115.0; extra == 'gateway'
